{
    "0shot": [
        {
            "count": "trip_planning_example_90",
            "final_program_time": {},
            "expected_time": {
                "itinerary": [
                    {
                        "day_range": "Day 1-5",
                        "place": "Naples"
                    },
                    {
                        "day_range": "Day 5",
                        "place": "Naples"
                    },
                    {
                        "day_range": "Day 5",
                        "place": "Vienna"
                    },
                    {
                        "day_range": "Day 6-11",
                        "place": "Vienna"
                    },
                    {
                        "day_range": "Day 11",
                        "place": "Vienna"
                    },
                    {
                        "day_range": "Day 11-17",
                        "place": "Vilnius"
                    }
                ]
            },
            "has_error": true,
            "is_correct": false
        }
    ]
}