{
    "0shot": [
        {
            "final_program_time": {},
            "expected_time": {
                "itinerary": [
                    {
                        "day_range": "Day 1-5",
                        "place": "Naples"
                    },
                    {
                        "day_range": "Day 5-9",
                        "place": "Dubrovnik"
                    },
                    {
                        "day_range": "Day 9-12",
                        "place": "Frankfurt"
                    },
                    {
                        "day_range": "Day 12-16",
                        "place": "Krakow"
                    },
                    {
                        "day_range": "Day 16-18",
                        "place": "Oslo"
                    }
                ]
            },
            "has_error": true,
            "count": "trip_planning_example_464"
        }
    ]
}