{
    "0shot": [
        {
            "count": "meeting_planning_example_6",
            "final_program_time": {
                "itinerary": [
                    {
                        "action": "meet",
                        "person": "Fisherman's Wharf",
                        "start_time": "09:00",
                        "end_time": "10:00"
                    }
                ]
            },
            "expected_time": {
                "itinerary": [
                    {
                        "action": "meet",
                        "person": "Kenneth",
                        "start_time": "14:15",
                        "end_time": "15:45"
                    }
                ]
            },
            "has_error": false,
            "is_correct": false
        }
    ]
}