{
    "0shot": [
        {
            "count": "trip_planning_example_240",
            "final_program_time": {
                "itinerary": [
                    {
                        "day_range": "Day 1",
                        "place": "Prague"
                    },
                    {
                        "day_range": "Day 2-5",
                        "place": "Stockholm"
                    },
                    {
                        "day_range": "Day 6-7",
                        "place": "Berlin"
                    },
                    {
                        "day_range": "Day 8-12",
                        "place": "Tallinn"
                    }
                ]
            },
            "expected_time": {
                "itinerary": [
                    {
                        "day_range": "Day 1-2",
                        "place": "Prague"
                    },
                    {
                        "day_range": "Day 2-6",
                        "place": "Stockholm"
                    },
                    {
                        "day_range": "Day 6-8",
                        "place": "Berlin"
                    },
                    {
                        "day_range": "Day 8-12",
                        "place": "Tallinn"
                    }
                ]
            },
            "has_error": false,
            "is_correct": false
        }
    ]
}