{
    "0shot": [
        {
            "count": "trip_planning_example_699",
            "final_program_time": {},
            "expected_time": {
                "itinerary": [
                    {
                        "day_range": "Day 1-2",
                        "place": "Hamburg"
                    },
                    {
                        "day_range": "Day 3-7",
                        "place": "Dublin"
                    },
                    {
                        "day_range": "Day 8-11",
                        "place": "Helsinki"
                    },
                    {
                        "day_range": "Day 12-13",
                        "place": "Reykjavik"
                    },
                    {
                        "day_range": "Day 14-18",
                        "place": "London"
                    },
                    {
                        "day_range": "Day 19-21",
                        "place": "Mykonos"
                    }
                ]
            },
            "has_error": true,
            "is_correct": false
        }
    ]
}