{
    "trip_planning_example_1374": {
        "input_query": [
            "You plan to visit 9 European cities for 21 days in total. You only take direct flights to commute between cities. You plan to stay in Reykjavik for 4 days. You want to spend 2 days in Berlin. You are going to attend a wedding in Berlin between day 14 and day 15. You want to spend 4 days in Edinburgh. You would like to meet your friends at Edinburgh between day 1 and day 4 to tour together. You plan to stay in London for 3 days. You want to meet a friend in London between day 11 and day 13. You want to spend 5 days in Porto. You would like to visit Seville for 3 days. You want to spend 2 days in Helsinki. You plan to visit relatives in Helsinki between day 13 and day 14. You would like to visit Krakow for 4 days. You would like to visit Paris for 2 days.\n\nHere are the cities that have direct flights:\nKrakow and London, Krakow and Paris, Reykjavik and London, Krakow and Helsinki, Edinburgh and Berlin, Edinburgh and Krakow, Helsinki and Berlin, Edinburgh and Helsinki, Paris and Helsinki, Edinburgh and Seville, Edinburgh and Paris, Reykjavik and Helsinki, Paris and Reykjavik, Porto and Seville, Berlin and Porto, Paris and London, London and Berlin, London and Helsinki, Krakow and Berlin, Reykjavik and Berlin, Paris and Porto, Edinburgh and Porto, Edinburgh and London, Paris and Seville, Paris and Berlin.\n\nFind a trip plan of visiting the cities for 21 days by taking direct flights to commute between them."
        ],
        "trip_length": 21,
        "city_length": [
            {
                "city": "Edinburgh",
                "days": 4
            },
            {
                "city": "Seville",
                "days": 3
            },
            {
                "city": "Porto",
                "days": 5
            },
            {
                "city": "Paris",
                "days": 2
            },
            {
                "city": "Reykjavik",
                "days": 4
            },
            {
                "city": "Helsinki",
                "days": 2
            },
            {
                "city": "Krakow",
                "days": 4
            },
            {
                "city": "Berlin",
                "days": 2
            },
            {
                "city": "London",
                "days": 3
            }
        ],
        "city_day_ranges": [
            {
                "city": "Edinburgh",
                "start": 1,
                "end": 4
            },
            {
                "city": "London",
                "start": 11,
                "end": 13
            },
            {
                "city": "Berlin",
                "start": 14,
                "end": 15
            },
            {
                "city": "Helsinki",
                "start": 13,
                "end": 14
            }
        ],
        "direct_flights": [
            {
                "from": "Krakow",
                "to": "London"
            },
            {
                "from": "Krakow",
                "to": "Paris"
            },
            {
                "from": "Reykjavik",
                "to": "London"
            },
            {
                "from": "Krakow",
                "to": "Helsinki"
            },
            {
                "from": "Edinburgh",
                "to": "Berlin"
            },
            {
                "from": "Edinburgh",
                "to": "Krakow"
            },
            {
                "from": "Helsinki",
                "to": "Berlin"
            },
            {
                "from": "Edinburgh",
                "to": "Helsinki"
            },
            {
                "from": "Paris",
                "to": "Helsinki"
            },
            {
                "from": "Edinburgh",
                "to": "Seville"
            },
            {
                "from": "Edinburgh",
                "to": "Paris"
            },
            {
                "from": "Reykjavik",
                "to": "Helsinki"
            },
            {
                "from": "Paris",
                "to": "Reykjavik"
            },
            {
                "from": "Porto",
                "to": "Seville"
            },
            {
                "from": "Berlin",
                "to": "Porto"
            },
            {
                "from": "Paris",
                "to": "London"
            },
            {
                "from": "London",
                "to": "Berlin"
            },
            {
                "from": "London",
                "to": "Helsinki"
            },
            {
                "from": "Krakow",
                "to": "Berlin"
            },
            {
                "from": "Reykjavik",
                "to": "Berlin"
            },
            {
                "from": "Paris",
                "to": "Porto"
            },
            {
                "from": "Edinburgh",
                "to": "Porto"
            },
            {
                "from": "Edinburgh",
                "to": "London"
            },
            {
                "from": "Paris",
                "to": "Seville"
            },
            {
                "from": "Paris",
                "to": "Berlin"
            }
        ]
    }
}