{
    "trip_planning_example_1144": {
        "input_query": [
            "You plan to visit 8 European cities for 20 days in total. You only take direct flights to commute between cities. You plan to stay in Dublin for 4 days. You want to spend 2 days in Porto. From day 6 to day 7, there is a annual show you want to attend in Porto. You would like to visit Prague for 4 days. You want to spend 3 days in Helsinki. You would like to visit Edinburgh for 4 days. You are going to attend a wedding in Edinburgh between day 7 and day 10. You want to spend 3 days in Valencia. You would like to meet your friends at Valencia between day 13 and day 15 to tour together. You plan to stay in Krakow for 4 days. You want to spend 3 days in Vilnius.\n\nHere are the cities that have direct flights:\nHelsinki and Vilnius, Prague and Krakow, Dublin and Porto, Helsinki and Dublin, Prague and Valencia, Porto and Edinburgh, Helsinki and Prague, Edinburgh and Prague, Dublin and Prague, Dublin and Valencia, Dublin and Edinburgh, Helsinki and Edinburgh, Valencia and Krakow, from Krakow to Vilnius, Porto and Valencia, Dublin and Krakow, Edinburgh and Krakow, Helsinki and Krakow.\n\nFind a trip plan of visiting the cities for 20 days by taking direct flights to commute between them."
        ],
        "trip_length": 20,
        "city_length": [
            {
                "city": "Dublin",
                "days": 4
            },
            {
                "city": "Porto",
                "days": 2
            },
            {
                "city": "Prague",
                "days": 4
            },
            {
                "city": "Helsinki",
                "days": 3
            },
            {
                "city": "Edinburgh",
                "days": 4
            },
            {
                "city": "Valencia",
                "days": 3
            },
            {
                "city": "Krakow",
                "days": 4
            },
            {
                "city": "Vilnius",
                "days": 3
            }
        ],
        "city_day_ranges": [
            {
                "city": "Porto",
                "start": 6,
                "end": 7,
                "event": "annual show"
            },
            {
                "city": "Edinburgh",
                "start": 7,
                "end": 10,
                "event": "wedding"
            },
            {
                "city": "Valencia",
                "start": 13,
                "end": 15,
                "event": "tour with friends"
            }
        ],
        "direct_flights": [
            {
                "from": "Helsinki",
                "to": "Vilnius"
            },
            {
                "from": "Prague",
                "to": "Krakow"
            },
            {
                "from": "Dublin",
                "to": "Porto"
            },
            {
                "from": "Helsinki",
                "to": "Dublin"
            },
            {
                "from": "Prague",
                "to": "Valencia"
            },
            {
                "from": "Porto",
                "to": "Edinburgh"
            },
            {
                "from": "Helsinki",
                "to": "Prague"
            },
            {
                "from": "Edinburgh",
                "to": "Prague"
            },
            {
                "from": "Dublin",
                "to": "Prague"
            },
            {
                "from": "Dublin",
                "to": "Valencia"
            },
            {
                "from": "Dublin",
                "to": "Edinburgh"
            },
            {
                "from": "Helsinki",
                "to": "Edinburgh"
            },
            {
                "from": "Valencia",
                "to": "Krakow"
            },
            {
                "from": "Krakow",
                "to": "Vilnius"
            },
            {
                "from": "Porto",
                "to": "Valencia"
            },
            {
                "from": "Dublin",
                "to": "Krakow"
            },
            {
                "from": "Edinburgh",
                "to": "Krakow"
            },
            {
                "from": "Helsinki",
                "to": "Krakow"
            }
        ]
    }
}