{
    "trip_planning_example_1469": {
        "input_query": [
            "You plan to visit 10 European cities for 16 days in total. You only take direct flights to commute between cities. You want to spend 2 days in Oslo. You plan to stay in Mykonos for 2 days. You want to meet a friend in Mykonos between day 9 and day 10. You plan to stay in Geneva for 4 days. You want to spend 2 days in Lisbon. You would like to visit Valencia for 2 days. You are going to attend a wedding in Valencia between day 5 and day 6. You would like to visit Reykjavik for 3 days. You want to spend 2 days in London. You would like to meet your friends at London between day 3 and day 4 to tour together. You plan to stay in Stockholm for 4 days. You plan to visit relatives in Stockholm between day 13 and day 16. You want to spend 2 days in Istanbul. From day 2 to day 3, there is a annual show you want to attend in Istanbul. You would like to visit Amsterdam for 2 days.\n\nHere are the cities that have direct flights:\nIstanbul and Amsterdam, Geneva and Mykonos, Oslo and Geneva, Istanbul and Stockholm, Istanbul and Valencia, Amsterdam and Stockholm, Oslo and London, Valencia and Geneva, Mykonos and Amsterdam, Oslo and Reykjavik, Amsterdam and Reykjavik, Geneva and Amsterdam, Valencia and Amsterdam, Geneva and Stockholm, London and Stockholm, London and Lisbon, London and Valencia, London and Amsterdam, Oslo and Istanbul, London and Reykjavik, Oslo and Lisbon, Lisbon and Amsterdam, Lisbon and Valencia, Istanbul and Lisbon, Lisbon and Stockholm, Oslo and Stockholm, Lisbon and Reykjavik, Lisbon and Geneva, Istanbul and London, Istanbul and Geneva, London and Mykonos, Reykjavik and Stockholm, London and Geneva, Oslo and Amsterdam."
        ],
        "trip_length": 16,
        "city_length": [
            {
                "city": "Oslo",
                "days": 2
            },
            {
                "city": "Istanbul",
                "days": 2
            },
            {
                "city": "London",
                "days": 2
            },
            {
                "city": "Valencia",
                "days": 2
            },
            {
                "city": "Geneva",
                "days": 4
            },
            {
                "city": "Amsterdam",
                "days": 2
            },
            {
                "city": "Reykjavik",
                "days": 3
            },
            {
                "city": "Lisbon",
                "days": 2
            },
            {
                "city": "Stockholm",
                "days": 4
            },
            {
                "city": "Mykonos",
                "days": 2
            }
        ],
        "city_day_ranges": [
            {
                "city": "Mykonos",
                "start": 9,
                "end": 10,
                "event": "Meet friend"
            },
            {
                "city": "Valencia",
                "start": 5,
                "end": 6,
                "event": "Attend wedding"
            },
            {
                "city": "London",
                "start": 3,
                "end": 4,
                "event": "Meet friends/tour together"
            },
            {
                "city": "Stockholm",
                "start": 13,
                "end": 16,
                "event": "Visit relatives"
            },
            {
                "city": "Istanbul",
                "start": 2,
                "end": 3,
                "event": "Annual show"
            }
        ],
        "direct_flights": [
            {
                "from": "Istanbul",
                "to": "Amsterdam"
            },
            {
                "from": "Geneva",
                "to": "Mykonos"
            },
            {
                "from": "Oslo",
                "to": "Geneva"
            },
            {
                "from": "Istanbul",
                "to": "Stockholm"
            },
            {
                "from": "Istanbul",
                "to": "Valencia"
            },
            {
                "from": "Amsterdam",
                "to": "Stockholm"
            },
            {
                "from": "Oslo",
                "to": "London"
            },
            {
                "from": "Valencia",
                "to": "Geneva"
            },
            {
                "from": "Mykonos",
                "to": "Amsterdam"
            },
            {
                "from": "Oslo",
                "to": "Reykjavik"
            },
            {
                "from": "Amsterdam",
                "to": "Reykjavik"
            },
            {
                "from": "Geneva",
                "to": "Amsterdam"
            },
            {
                "from": "Valencia",
                "to": "Amsterdam"
            },
            {
                "from": "Geneva",
                "to": "Stockholm"
            },
            {
                "from": "London",
                "to": "Stockholm"
            },
            {
                "from": "London",
                "to": "Lisbon"
            },
            {
                "from": "London",
                "to": "Valencia"
            },
            {
                "from": "London",
                "to": "Amsterdam"
            },
            {
                "from": "Oslo",
                "to": "Istanbul"
            },
            {
                "from": "London",
                "to": "Reykjavik"
            },
            {
                "from": "Oslo",
                "to": "Lisbon"
            },
            {
                "from": "Lisbon",
                "to": "Amsterdam"
            },
            {
                "from": "Lisbon",
                "to": "Valencia"
            },
            {
                "from": "Istanbul",
                "to": "Lisbon"
            },
            {
                "from": "Lisbon",
                "to": "Stockholm"
            },
            {
                "from": "Oslo",
                "to": "Stockholm"
            },
            {
                "from": "Lisbon",
                "to": "Reykjavik"
            },
            {
                "from": "Lisbon",
                "to": "Geneva"
            },
            {
                "from": "Istanbul",
                "to": "London"
            },
            {
                "from": "Istanbul",
                "to": "Geneva"
            },
            {
                "from": "London",
                "to": "Mykonos"
            },
            {
                "from": "Reykjavik",
                "to": "Stockholm"
            },
            {
                "from": "London",
                "to": "Geneva"
            },
            {
                "from": "Oslo",
                "to": "Amsterdam"
            }
        ],
        "possible_trip_route": [
            {
                "city": "Oslo",
                "start_day": 1,
                "end_day": 2
            },
            {
                "city": "Istanbul",
                "start_day": 2,
                "end_day": 3
            },
            {
                "city": "London",
                "start_day": 3,
                "end_day": 4
            },
            {
                "city": "Valencia",
                "start_day": 5,
                "end_day": 6
            },
            {
                "city": "Geneva",
                "start_day": 7,
                "end_day": 10
            },
            {
                "city": "Mykonos",
                "start_day": 9,
                "end_day": 10
            },
            {
                "city": "Amsterdam",
                "start_day": 11,
                "end_day": 12
            },
            {
                "city": "Reykjavik",
                "start_day": 12,
                "end_day": 14
            },
            {
                "city": "Lisbon",
                "start_day": 14,
                "end_day": 15
            },
            {
                "city": "Stockholm",
                "start_day": 13,
                "end_day": 16
            }
        ]
    }
}