{
    "itinerary": [
        {
            "day_range": "Day 1-4",
            "place": "Geneva"
        },
        {
            "day_range": "Day 5-8",
            "place": "Vienna"
        },
        {
            "day_range": "Day 9-13",
            "place": "Venice"
        },
        {
            "day_range": "Day 14-17",
            "place": "Istanbul"
        },
        {
            "day_range": "Day 18-19",
            "place": "Reykjavik"
        },
        {
            "day_range": "Day 20-23",
            "place": "Vilnius"
        },
        {
            "day_range": "Day 24-25",
            "place": "Riga"
        },
        {
            "day_range": "Day 26-27",
            "place": "Brussels"
        }
    ]
}