{
    "0shot": [
        {
            "final_program_time": {
                "itinerary": [
                    {
                        "action": "meet",
                        "location": "Mission District",
                        "person": "William",
                        "start_time": "9:07",
                        "end_time": "9:37"
                    },
                    {
                        "action": "meet",
                        "location": "Golden Gate Park",
                        "person": "Robert",
                        "start_time": "9:44",
                        "end_time": "10:29"
                    },
                    {
                        "action": "meet",
                        "location": "Russian Hill",
                        "person": "Mark",
                        "start_time": "10:36",
                        "end_time": "11:51"
                    },
                    {
                        "action": "meet",
                        "location": "Haight-Ashbury",
                        "person": "Elizabeth",
                        "start_time": "12:08",
                        "end_time": "13:53"
                    },
                    {
                        "action": "meet",
                        "location": "Sunset District",
                        "person": "Linda",
                        "start_time": "14:10",
                        "end_time": "14:40"
                    },
                    {
                        "action": "meet",
                        "location": "Presidio",
                        "person": "Rebecca",
                        "start_time": "14:51",
                        "end_time": "15:51"
                    }
                ]
            },
            "expected_time": {
                "itinerary": [
                    {
                        "action": "meet",
                        "location": "Mission District",
                        "person": "William",
                        "start_time": "13:15",
                        "end_time": "13:45"
                    },
                    {
                        "action": "meet",
                        "location": "Golden Gate Park",
                        "person": "Robert",
                        "start_time": "14:15",
                        "end_time": "15:00"
                    },
                    {
                        "action": "meet",
                        "location": "Russian Hill",
                        "person": "Mark",
                        "start_time": "15:19",
                        "end_time": "16:34"
                    },
                    {
                        "action": "meet",
                        "location": "Sunset District",
                        "person": "Linda",
                        "start_time": "16:57",
                        "end_time": "17:27"
                    },
                    {
                        "action": "meet",
                        "location": "Haight-Ashbury",
                        "person": "Elizabeth",
                        "start_time": "17:42",
                        "end_time": "19:27"
                    },
                    {
                        "action": "meet",
                        "location": "Presidio",
                        "person": "Rebecca",
                        "start_time": "19:42",
                        "end_time": "20:42"
                    }
                ]
            },
            "count": "meeting_planning_example_575",
            "is_correct": false
        }
    ]
}