{
    "itinerary": [
        {
            "day_range": "Day 1-2",
            "place": "Seville"
        },
        {
            "day_range": "Day 3-6",
            "place": "Vienna"
        },
        {
            "day_range": "Day 6-7",
            "place": "Madrid"
        },
        {
            "day_range": "Day 8-11",
            "place": "Frankfurt"
        },
        {
            "day_range": "Day 12-16",
            "place": "Krakow"
        },
        {
            "day_range": "Day 17-19",
            "place": "Bucharest"
        },
        {
            "day_range": "Day 20-23",
            "place": "Riga"
        },
        {
            "day_range": "Day 23-26",
            "place": "Tallinn"
        },
        {
            "day_range": "Day 26-27",
            "place": "Valencia"
        },
        {
            "day_range": "Day 27",
            "place": "Santorini"
        }
    ]
}