{
    "itinerary": [
        {
            "day_range": "Day 1-5",
            "place": "Oslo"
        },
        {
            "day_range": "Day 5-6",
            "place": "Reykjavik"
        },
        {
            "day_range": "Day 6-10",
            "place": "Stuttgart"
        },
        {
            "day_range": "Day 10-11",
            "place": "Geneva"
        },
        {
            "day_range": "Day 11-13",
            "place": "Porto"
        },
        {
            "day_range": "Day 13-15",
            "place": "Split"
        },
        {
            "day_range": "Day 15-17",
            "place": "Stockholm"
        },
        {
            "day_range": "Day 17-21",
            "place": "Tallinn"
        }
    ]
}