{
    "meeting_planning_example_207": {
        "input_query": [
            "You are visiting San Francisco for the day and want to meet as many friends as possible. Solve the problem by considering various different schedules and picking the best one to optimize your goals.\n\nTravel distances (in minutes):\nPacific Heights to Golden Gate Park: 15.\nPacific Heights to Bayview: 22.\nPacific Heights to Marina District: 6.\nGolden Gate Park to Pacific Heights: 16.\nGolden Gate Park to Bayview: 23.\nGolden Gate Park to Marina District: 16.\nBayview to Pacific Heights: 23.\nBayview to Golden Gate Park: 22.\nBayview to Marina District: 25.\nMarina District to Pacific Heights: 7.\nMarina District to Golden Gate Park: 18.\nMarina District to Bayview: 27.\n\nCONSTRAINTS: You arrive at Pacific Heights at 9:00AM. Richard will be at Golden Gate Park from 12:15PM to 4:00PM. You'd like to meet Richard for a minimum of 120 minutes. Betty will be at Bayview from 7:15AM to 9:30PM. You'd like to meet Betty for a minimum of 120 minutes. Jeffrey will be at Marina District from 9:15AM to 4:45PM. You'd like to meet Jeffrey for a minimum of 75 minutes.\n\nYour response should start with 'SOLUTION:'."
        ],
        "travel_distances": [
            {
                "place": {
                    "from": "Pacific Heights",
                    "to": "Golden Gate Park"
                },
                "walking_time": 15
            },
            {
                "place": {
                    "from": "Pacific Heights",
                    "to": "Bayview"
                },
                "walking_time": 22
            },
            {
                "place": {
                    "from": "Pacific Heights",
                    "to": "Marina District"
                },
                "walking_time": 6
            },
            {
                "place": {
                    "from": "Golden Gate Park",
                    "to": "Pacific Heights"
                },
                "walking_time": 16
            },
            {
                "place": {
                    "from": "Golden Gate Park",
                    "to": "Bayview"
                },
                "walking_time": 23
            },
            {
                "place": {
                    "from": "Golden Gate Park",
                    "to": "Marina District"
                },
                "walking_time": 16
            },
            {
                "place": {
                    "from": "Bayview",
                    "to": "Pacific Heights"
                },
                "walking_time": 23
            },
            {
                "place": {
                    "from": "Bayview",
                    "to": "Golden Gate Park"
                },
                "walking_time": 22
            },
            {
                "place": {
                    "from": "Bayview",
                    "to": "Marina District"
                },
                "walking_time": 25
            },
            {
                "place": {
                    "from": "Marina District",
                    "to": "Pacific Heights"
                },
                "walking_time": 7
            },
            {
                "place": {
                    "from": "Marina District",
                    "to": "Golden Gate Park"
                },
                "walking_time": 18
            },
            {
                "place": {
                    "from": "Marina District",
                    "to": "Bayview"
                },
                "walking_time": 27
            }
        ],
        "constraints": [
            {
                "location": "Pacific Heights",
                "time_of_day": 9.0
            },
            {
                "person": "Richard",
                "location": "Golden Gate Park",
                "duration": {
                    "from": 12.25,
                    "to": 16.0
                },
                "min_meeting_duration": 120
            },
            {
                "person": "Betty",
                "location": "Bayview",
                "duration": {
                    "from": 7.25,
                    "to": 21.5
                },
                "min_meeting_duration": 120
            },
            {
                "person": "Jeffrey",
                "location": "Marina District",
                "duration": {
                    "from": 9.25,
                    "to": 16.75
                },
                "min_meeting_duration": 75
            }
        ]
    }
}