{
    "meeting_planning_example_260": {
        "input_query": [
            "You are visiting San Francisco for the day and want to meet as many friends as possible. Solve the problem by considering various different schedules and picking the best one to optimize your goals.\n\nTravel distances (in minutes):\nThe Castro to Russian Hill: 18.\nThe Castro to Alamo Square: 8.\nThe Castro to Embarcadero: 22.\nRussian Hill to The Castro: 21.\nRussian Hill to Alamo Square: 15.\nRussian Hill to Embarcadero: 8.\nAlamo Square to The Castro: 8.\nAlamo Square to Russian Hill: 13.\nAlamo Square to Embarcadero: 17.\nEmbarcadero to The Castro: 25.\nEmbarcadero to Russian Hill: 8.\nEmbarcadero to Alamo Square: 19.\n\nCONSTRAINTS: You arrive at The Castro at 9:00AM. Barbara will be at Russian Hill from 4:00PM to 8:45PM. You'd like to meet Barbara for a minimum of 60 minutes. Steven will be at Alamo Square from 8:15PM to 9:45PM. You'd like to meet Steven for a minimum of 90 minutes. Brian will be at Embarcadero from 6:30PM to 9:45PM. You'd like to meet Brian for a minimum of 90 minutes.\n\nYour response should start with 'SOLUTION:'."
        ],
        "travel_distances": [
            {
                "place": {
                    "from": "The Castro",
                    "to": "Russian Hill"
                },
                "walking_time": 18
            },
            {
                "place": {
                    "from": "The Castro",
                    "to": "Alamo Square"
                },
                "walking_time": 8
            },
            {
                "place": {
                    "from": "The Castro",
                    "to": "Embarcadero"
                },
                "walking_time": 22
            },
            {
                "place": {
                    "from": "Russian Hill",
                    "to": "The Castro"
                },
                "walking_time": 21
            },
            {
                "place": {
                    "from": "Russian Hill",
                    "to": "Alamo Square"
                },
                "walking_time": 15
            },
            {
                "place": {
                    "from": "Russian Hill",
                    "to": "Embarcadero"
                },
                "walking_time": 8
            },
            {
                "place": {
                    "from": "Alamo Square",
                    "to": "The Castro"
                },
                "walking_time": 8
            },
            {
                "place": {
                    "from": "Alamo Square",
                    "to": "Russian Hill"
                },
                "walking_time": 13
            },
            {
                "place": {
                    "from": "Alamo Square",
                    "to": "Embarcadero"
                },
                "walking_time": 17
            },
            {
                "place": {
                    "from": "Embarcadero",
                    "to": "The Castro"
                },
                "walking_time": 25
            },
            {
                "place": {
                    "from": "Embarcadero",
                    "to": "Russian Hill"
                },
                "walking_time": 8
            },
            {
                "place": {
                    "from": "Embarcadero",
                    "to": "Alamo Square"
                },
                "walking_time": 19
            }
        ],
        "constraints": [
            {
                "location": "The Castro",
                "time_of_day": 9
            },
            {
                "person": "Barbara",
                "location": "Russian Hill",
                "duration": {
                    "from": 16,
                    "to": 20.75
                },
                "min_meeting_duration": 60
            },
            {
                "person": "Steven",
                "location": "Alamo Square",
                "duration": {
                    "from": 20.25,
                    "to": 21.75
                },
                "min_meeting_duration": 90
            },
            {
                "person": "Brian",
                "location": "Embarcadero",
                "duration": {
                    "from": 18.5,
                    "to": 21.75
                },
                "min_meeting_duration": 90
            }
        ]
    }
}